{
	"info": {
		"_postman_id": "149dfd91-9295-4adc-a2ad-ffcfd3072e16",
		"name": "Мой первый API",
		"schema": "https://schema.getpostman.com/json/collection/v2.1.0/collection.json",
		"_exporter_id": "47919358",
		"_collection_link": "https://alexander-sidorenko-s-team.postman.co/workspace/0535557b-68e3-49fb-88bf-251ff57aca0d/collection/47919358-149dfd91-9295-4adc-a2ad-ffcfd3072e16?action=share&source=collection_link&creator=47919358"
	},
	"item": [
		{
			"name": "Получение информации о выбранном посте",
			"request": {
				"method": "GET",
				"header": [
					{
						"key": "Content-Type",
						"value": "application/json",
						"type": "text"
					}
				],
				"url": {
					"raw": "https://jsonplaceholder.typicode.com/posts/:postID",
					"protocol": "https",
					"host": [
						"jsonplaceholder",
						"typicode",
						"com"
					],
					"path": [
						"posts",
						":postID"
					],
					"variable": [
						{
							"key": "postID",
							"value": "5"
						}
					]
				}
			},
			"response": []
		},
		{
			"name": "Создание поста",
			"request": {
				"method": "POST",
				"header": [
					{
						"key": "Content-Type",
						"value": "application/json",
						"type": "text"
					}
				],
				"body": {
					"mode": "raw",
					"raw": "{\r\n    \"title\": \"foo\",\r\n    \"body\": \"bar\", \r\n    \"userId\": 1\r\n}",
					"options": {
						"raw": {
							"language": "json"
						}
					}
				},
				"url": {
					"raw": "https://jsonplaceholder.typicode.com/posts",
					"protocol": "https",
					"host": [
						"jsonplaceholder",
						"typicode",
						"com"
					],
					"path": [
						"posts"
					]
				}
			},
			"response": []
		},
		{
			"name": "Обновление информации о выбранном посте",
			"request": {
				"method": "PUT",
				"header": [
					{
						"key": "Content-Type",
						"value": "application/json",
						"type": "text"
					}
				],
				"body": {
					"mode": "raw",
					"raw": "{\r\n    \"id\": 1,\r\n    \"title\": \"updated title\",\r\n    \"body\": \"updated body\",\r\n    \"userId\": 1\r\n}",
					"options": {
						"raw": {
							"language": "json"
						}
					}
				},
				"url": {
					"raw": "https://jsonplaceholder.typicode.com/posts/:postID",
					"protocol": "https",
					"host": [
						"jsonplaceholder",
						"typicode",
						"com"
					],
					"path": [
						"posts",
						":postID"
					],
					"variable": [
						{
							"key": "postID",
							"value": "5"
						}
					]
				}
			},
			"response": []
		},
		{
			"name": "Удаление выбранного поста",
			"request": {
				"method": "DELETE",
				"header": [
					{
						"key": "Content-Type",
						"value": "application/json",
						"type": "text"
					}
				],
				"url": {
					"raw": "https://jsonplaceholder.typicode.com/posts/:postID",
					"protocol": "https",
					"host": [
						"jsonplaceholder",
						"typicode",
						"com"
					],
					"path": [
						"posts",
						":postID"
					],
					"variable": [
						{
							"key": "postID",
							"value": "2"
						}
					]
				}
			},
			"response": []
		}
	],
	"variable": [
		{
			"key": "postID",
			"value": "",
			"type": "default"
		}
	]
}